family/__init__.py
family/commands/__init__.py
family/commands/createapp.py
family/templates/__init__.py
family/templates/basic.py
family/templates/common_wsgi/__init__.py
family/templates/common_wsgi/gitignore_tmpl
family/templates/common_wsgi/setup.py_tmpl
family/templates/common_wsgi/shell.py
family/templates/common_wsgi/+package+/__init__.py
family/templates/common_wsgi/+package+/local_settings.py_tmpl
family/templates/common_wsgi/+package+/middlewares.py_tmpl
family/templates/common_wsgi/+package+/models.py_tmpl
family/templates/common_wsgi/+package+/sentry.py_tmpl
family/templates/common_wsgi/+package+/settings.py_tmpl
family/templates/common_wsgi/+package+/wsgi.py_tmpl
family/templates/common_wsgi/configs/alembic-dev.ini_tmpl
family/templates/common_wsgi/configs/alembic.ini_tmpl
family/templates/common_wsgi/configs/gunicorn_development.py_tmpl
family/templates/common_wsgi/configs/gunicorn_production.py_tmpl
family/templates/common_wsgi/configs/supervisor.ini_tmpl
family/templates/common_wsgi/configs/uwsgi.ini_tmpl
family/templates/common_wsgi/scripts/fabfile.py_tmpl
family/templates/falcon/+package+/app.py_tmpl
family/templates/falcon/requirements/base.txt_tmpl
family/templates/falcon/requirements/internal.txt_tmpl
family/templates/flask/+package+/app.py_tmpl
family/templates/flask/requirements/base.txt_tmpl
family/templates/flask/requirements/internal.txt_tmpl
family-0.9.10.dist-info/DESCRIPTION.rst
family-0.9.10.dist-info/METADATA
family-0.9.10.dist-info/RECORD
family-0.9.10.dist-info/WHEEL
family-0.9.10.dist-info/entry_points.txt
family-0.9.10.dist-info/metadata.json
family-0.9.10.dist-info/top_level.txt
