Metadata-Version: 2.0
Name: family
Version: 0.9.10
Summary: Easy to create your microservice based on multiple python frameworks.
Home-page: https://github.com/torpedoallen/family
Author: torpedoallen
Author-email: torpedoallen@gmail.com
License: MIT
Keywords: microservice falcon flask
Platform: UNKNOWN
Requires-Dist: PasteScript
Requires-Dist: check-manifest
Requires-Dist: click
Requires-Dist: wheel
